{
  "name": "Author",
  "fields": [
    {
      "fieldName": "fistName",
      "fieldType": "String",
      "fieldValidateRules": ["required"]
    },
    {
      "fieldName": "lastName",
      "fieldType": "String",
      "fieldValidateRules": ["required"]
    }
  ],
  "relationships": [
    {
      "relationshipType": "many-to-many",
      "otherEntityName": "book",
      "otherEntityRelationshipName": "author",
      "relationshipName": "book",
      "ownerSide": false
    }
  ],
  "entityTableName": "author",
  "dto": "no",
  "pagination": "no",
  "service": "serviceImpl",
  "jpaMetamodelFiltering": false,
  "fluentMethods": true,
  "readOnly": false,
  "embedded": false,
  "applications": "*",
  "changelogDate": "20230419183027"
}
